ispyb_client/__init__.py
ispyb_client/api_client.py
ispyb_client/configuration.py
ispyb_client/exceptions.py
ispyb_client/rest.py
ispyb_client/schemas.py
ispyb_client/apis/__init__.py
ispyb_client/apis/path_to_api.py
ispyb_client/apis/tag_to_api.py
ispyb_client/apis/paths/__init__.py
ispyb_client/apis/paths/ispyb_api_v1_admin_activity.py
ispyb_client/apis/paths/ispyb_api_v1_auth_config.py
ispyb_client/apis/paths/ispyb_api_v1_auth_login.py
ispyb_client/apis/paths/ispyb_api_v1_datacollections_attachments.py
ispyb_client/apis/paths/ispyb_api_v1_datacollections_attachments_data_collection_file_attachment_id.py
ispyb_client/apis/paths/ispyb_api_v1_datacollections_images_data_collection_id.py
ispyb_client/apis/paths/ispyb_api_v1_datacollections_images_diffraction_data_collection_id.py
ispyb_client/apis/paths/ispyb_api_v1_datacollections_images_quality_data_collection_id.py
ispyb_client/apis/paths/ispyb_api_v1_datacollections_quality.py
ispyb_client/apis/paths/ispyb_api_v1_datacollections_workflows_steps.py
ispyb_client/apis/paths/ispyb_api_v1_datacollections_workflows_steps_workflow_step_id.py
ispyb_client/apis/paths/ispyb_api_v1_eventchain.py
ispyb_client/apis/paths/ispyb_api_v1_events.py
ispyb_client/apis/paths/ispyb_api_v1_events_types.py
ispyb_client/apis/paths/ispyb_api_v1_labcontacts.py
ispyb_client/apis/paths/ispyb_api_v1_labcontacts_lab_contact_id.py
ispyb_client/apis/paths/ispyb_api_v1_legacy_data_collections_groups_session_session_id.py
ispyb_client/apis/paths/ispyb_api_v1_legacy_em_proposal_proposal_id_data_collections_data_collections_ids_stats.py
ispyb_client/apis/paths/ispyb_api_v1_legacy_em_proposal_proposal_id_data_collections_group_data_collections_group_id_stats.py
ispyb_client/apis/paths/ispyb_api_v1_legacy_em_proposal_proposal_id_datacollection_datacollection_id_movies.py
ispyb_client/apis/paths/ispyb_api_v1_legacy_em_proposal_proposal_id_movie_movie_id_plot_motioncorrectiondrift.py
ispyb_client-1.0.0.dist-info/METADATA
ispyb_client-1.0.0.dist-info/WHEEL
ispyb_client-1.0.0.dist-info/top_level.txt
ispyb_client-1.0.0.dist-info/RECORD
